{
    "phase": "coref",
    "clusters": [
        {
            "members": [
                0,
                11
            ],
            "source": [
                "new",
                "new",
                "new"
            ],
            "id": 0
        },
        {
            "members": [
                1,
                104,
                83,
                51,
                91
            ],
            "source": [
                "new",
                "new",
                "new"
            ],
            "id": 1
        },
        {
            "members": [
                8,
                2
            ],
            "source": [
                "new",
                "new",
                "new"
            ],
            "id": 2
        },
        {
            "members": [
                4
            ],
            "source": [
                "new",
                "new",
                "new"
            ],
            "id": 3
        },
        {
            "members": [
                7
            ],
            "source": [
                "new",
                "new",
                "new"
            ],
            "id": 4
        },
        {
            "members": [
                9,
                13
            ],
            "source": [
                "new",
                "new",
                "new"
            ],
            "id": 5
        },
        {
            "members": [
                10
            ],
            "source": [
                "new",
                "new",
                "new"
            ],
            "id": 6
        },
        {
            "members": [
                12
            ],
            "source": [
                "new",
                "new",
                "new"
            ],
            "id": 7
        },
        {
            "members": [
                14
            ],
            "source": [
                "new",
                "new",
                "new"
            ],
            "id": 8
        },
        {
            "members": [
                16,
                15
            ],
            "source": [
                "new",
                "new",
                "new"
            ],
            "id": 9
        },
        {
            "members": [
                24,
                17,
                20,
                21
            ],
            "source": [
                "new",
                "new",
                "new"
            ],
            "id": 10
        },
        {
            "members": [
                23
            ],
            "source": [
                "new",
                "new",
                "new"
            ],
            "id": 11
        },
        {
            "members": [
                26
            ],
            "source": [
                "new",
                "new",
                "new"
            ],
            "id": 13
        },
        {
            "members": [
                99,
                35,
                37,
                103,
                42,
                78,
                48,
                53,
                54,
                58,
                27,
                63
            ],
            "source": [
                "new",
                "new",
                "new"
            ],
            "id": 14
        },
        {
            "members": [
                28
            ],
            "source": [
                "new",
                "new",
                "new"
            ],
            "id": 15
        },
        {
            "members": [
                30
            ],
            "source": [
                "new",
                "new",
                "new"
            ],
            "id": 16
        },
        {
            "members": [
                34,
                101,
                38,
                75,
                52,
                31
            ],
            "source": [
                "new",
                "new",
                "new"
            ],
            "id": 17
        },
        {
            "members": [
                32,
                96
            ],
            "source": [
                "new",
                "new",
                "new"
            ],
            "id": 18
        },
        {
            "members": [
                33
            ],
            "source": [
                "new",
                "new",
                "new"
            ],
            "id": 19
        },
        {
            "members": [
                36
            ],
            "source": [
                "new",
                "new",
                "new"
            ],
            "id": 20
        },
        {
            "members": [
                39
            ],
            "source": [
                "new",
                "new",
                "new"
            ],
            "id": 21
        },
        {
            "members": [
                40
            ],
            "source": [
                "new",
                "new",
                "new"
            ],
            "id": 22
        },
        {
            "members": [
                41
            ],
            "source": [
                "new",
                "new",
                "new"
            ],
            "id": 23
        },
        {
            "members": [
                44
            ],
            "source": [
                "new",
                "new",
                "new"
            ],
            "id": 24
        },
        {
            "members": [
                45
            ],
            "source": [
                "new",
                "new",
                "new"
            ],
            "id": 25
        },
        {
            "members": [
                46
            ],
            "source": [
                "new",
                "new",
                "new"
            ],
            "id": 26
        },
        {
            "members": [
                47
            ],
            "source": [
                "new",
                "new",
                "new"
            ],
            "id": 27
        },
        {
            "members": [
                49,
                84
            ],
            "source": [
                "new",
                "new",
                "new"
            ],
            "id": 28
        },
        {
            "members": [
                55
            ],
            "source": [
                "new",
                "new",
                "new"
            ],
            "id": 29
        },
        {
            "members": [
                57
            ],
            "source": [
                "new",
                "new",
                "new"
            ],
            "id": 30
        },
        {
            "members": [
                59
            ],
            "source": [
                "new",
                "new",
                "new"
            ],
            "id": 31
        },
        {
            "members": [
                60,
                80
            ],
            "source": [
                "new",
                "new",
                "new"
            ],
            "id": 32
        },
        {
            "members": [
                61
            ],
            "source": [
                "new",
                "new",
                "new"
            ],
            "id": 33
        },
        {
            "members": [
                62
            ],
            "source": [
                "new",
                "new",
                "new"
            ],
            "id": 34
        },
        {
            "members": [
                64
            ],
            "source": [
                "new",
                "new",
                "new"
            ],
            "id": 35
        },
        {
            "members": [
                65
            ],
            "source": [
                "new",
                "new",
                "new"
            ],
            "id": 36
        },
        {
            "members": [
                66
            ],
            "source": [
                "new",
                "new",
                "new"
            ],
            "id": 37
        },
        {
            "members": [
                67
            ],
            "source": [
                "new",
                "new",
                "new"
            ],
            "id": 38
        },
        {
            "members": [
                68
            ],
            "source": [
                "new",
                "new",
                "new"
            ],
            "id": 39
        },
        {
            "members": [
                69
            ],
            "source": [
                "new",
                "new",
                "new"
            ],
            "id": 40
        },
        {
            "members": [
                70
            ],
            "source": [
                "new",
                "new",
                "new"
            ],
            "id": 41
        },
        {
            "members": [
                73
            ],
            "source": [
                "new",
                "new",
                "new"
            ],
            "id": 43
        },
        {
            "members": [
                79
            ],
            "source": [
                "new",
                "new",
                "new"
            ],
            "id": 45
        },
        {
            "members": [
                81
            ],
            "source": [
                "new",
                "new",
                "new"
            ],
            "id": 46
        },
        {
            "members": [
                82
            ],
            "source": [
                "new",
                "new",
                "new"
            ],
            "id": 47
        },
        {
            "members": [
                86
            ],
            "source": [
                "new",
                "new",
                "new"
            ],
            "id": 48
        },
        {
            "members": [
                87
            ],
            "source": [
                "new",
                "new",
                "new"
            ],
            "id": 49
        },
        {
            "members": [
                89
            ],
            "source": [
                "new",
                "new",
                "new"
            ],
            "id": 50
        },
        {
            "members": [
                90
            ],
            "source": [
                "new",
                "new",
                "new"
            ],
            "id": 51
        },
        {
            "members": [
                92
            ],
            "source": [
                "new",
                "new",
                "new"
            ],
            "id": 52
        },
        {
            "members": [
                93
            ],
            "source": [
                "new",
                "new",
                "new"
            ],
            "id": 53
        },
        {
            "members": [
                94
            ],
            "source": [
                "new",
                "new",
                "new"
            ],
            "id": 54
        },
        {
            "members": [
                97
            ],
            "source": [
                "new",
                "new",
                "new"
            ],
            "id": 55
        },
        {
            "members": [
                98
            ],
            "source": [
                "new",
                "new",
                "new"
            ],
            "id": 56
        },
        {
            "members": [
                100
            ],
            "source": [
                "new",
                "new",
                "new"
            ],
            "id": 57
        },
        {
            "id": 58,
            "members": [
                3,
                22
            ],
            "source": "new"
        },
        {
            "id": 59,
            "members": [
                5,
                19,
                74
            ],
            "source": "new"
        },
        {
            "id": 60,
            "members": [
                6
            ],
            "source": "idiomatic"
        },
        {
            "id": 61,
            "members": [
                18,
                85
            ],
            "source": "new"
        },
        {
            "id": 62,
            "members": [
                25
            ],
            "source": "idiomatic"
        },
        {
            "id": 63,
            "members": [
                29
            ],
            "source": "new"
        },
        {
            "id": 64,
            "members": [
                43,
                56
            ],
            "source": "new"
        },
        {
            "id": 65,
            "members": [
                50
            ],
            "source": "new"
        },
        {
            "id": 66,
            "members": [
                71,
                88,
                95
            ],
            "source": "new"
        },
        {
            "id": 67,
            "members": [
                72
            ],
            "source": "idiomatic"
        },
        {
            "id": 68,
            "members": [
                76
            ],
            "source": "idiomatic"
        },
        {
            "id": 69,
            "members": [
                77
            ],
            "source": "new"
        },
        {
            "id": 70,
            "members": [
                102
            ],
            "source": "idiomatic"
        }
    ],
    "states": {
        "3": {
            "selected_coref_option": "new"
        },
        "5": {
            "selected_coref_option": "new"
        },
        "6": {
            "selected_coref_option": "idiomatic"
        },
        "18": {
            "selected_coref_option": "new"
        },
        "19": {
            "selected_coref_option": "same as..."
        },
        "21": {
            "selected_coref_option": "same as..."
        },
        "22": {
            "selected_coref_option": "same as..."
        },
        "25": {
            "selected_coref_option": "idiomatic"
        },
        "29": {
            "selected_coref_option": "new"
        },
        "43": {
            "selected_coref_option": "new"
        },
        "50": {
            "selected_coref_option": "new"
        },
        "56": {
            "selected_coref_option": "same as..."
        },
        "71": {
            "selected_coref_option": "new"
        },
        "72": {
            "selected_coref_option": "idiomatic"
        },
        "74": {
            "selected_coref_option": "same as..."
        },
        "76": {
            "selected_coref_option": "idiomatic"
        },
        "77": {
            "selected_coref_option": "new"
        },
        "80": {
            "selected_coref_option": "same as..."
        },
        "85": {
            "selected_coref_option": "same as..."
        },
        "88": {
            "selected_coref_option": "same as..."
        },
        "95": {
            "selected_coref_option": "same as..."
        },
        "102": {
            "selected_coref_option": "idiomatic"
        }
    },
    "hit_id": 94,
    "nps": [
        {
            "text": "השופטת עדנה גבריאלי מבית-הדין לה_עבודה בתל-אביב",
            "start_index": 7,
            "end_index": 54,
            "id": 0,
            "start_token": 0,
            "end_token": 16,
            "sent_num": 0
        },
        {
            "text": "בית-הדין לה_עבודה בתל-אביב",
            "start_index": 28,
            "end_index": 54,
            "id": 1,
            "start_token": 5,
            "end_token": 16,
            "sent_num": 0
        },
        {
            "text": "תל-אביב",
            "start_index": 47,
            "end_index": 54,
            "id": 2,
            "start_token": 13,
            "end_token": 16,
            "sent_num": 0
        },
        {
            "text": "צו ביניים שלא לעשות כל שינוי בנכסי דיור לה_עולה ברח חשמונאים 19 בתל-אביב, עד לה_דיון שייערך בפנים_של__היא בה_19 בנובמבר, ב_הוא תישמע בקשה_של__הוא של המנכ\"ל לשעבר של החברה להגדיל את העיקול הזמני על נכסי חברת דיור לה_עולה בע\"ם",
            "start_index": 62,
            "end_index": 286,
            "id": 3,
            "start_token": 17,
            "end_token": 81,
            "sent_num": 0
        },
        {
            "text": "כל שינוי בנכסי דיור לה_עולה ברח חשמונאים 19 בתל-אביב",
            "start_index": 82,
            "end_index": 134,
            "id": 4,
            "start_token": 21,
            "end_token": 37,
            "sent_num": 0
        },
        {
            "text": "נכסי דיור לה_עולה ברח חשמונאים 19 בתל-אביב",
            "start_index": 92,
            "end_index": 134,
            "id": 5,
            "start_token": 24,
            "end_token": 37,
            "sent_num": 0
        },
        {
            "text": "רח חשמונאים 19 בתל-אביב",
            "start_index": 111,
            "end_index": 134,
            "id": 7,
            "start_token": 30,
            "end_token": 37,
            "sent_num": 0
        },
        {
            "text": "תל-אביב",
            "start_index": 127,
            "end_index": 134,
            "id": 8,
            "start_token": 34,
            "end_token": 37,
            "sent_num": 0
        },
        {
            "text": "ה_דיון שייערך בפנים_של__היא בה_19 בנובמבר, ב_הוא תישמע בקשה_של__הוא של המנכ\"ל לשעבר של החברה להגדיל את העיקול הזמני על נכסי חברת דיור לה_עולה בע\"ם",
            "start_index": 140,
            "end_index": 286,
            "id": 9,
            "start_token": 40,
            "end_token": 81,
            "sent_num": 0
        },
        {
            "text": "פנים_של__היא",
            "start_index": 155,
            "end_index": 167,
            "id": 10,
            "start_token": 45,
            "end_token": 48,
            "sent_num": 0
        },
        {
            "text": "_היא",
            "start_index": 163,
            "end_index": 167,
            "id": 11,
            "start_token": 47,
            "end_token": 48,
            "sent_num": 0
        },
        {
            "text": "ה_19 בנובמבר",
            "start_index": 169,
            "end_index": 181,
            "id": 12,
            "start_token": 49,
            "end_token": 53,
            "sent_num": 0
        },
        {
            "text": "_הוא",
            "start_index": 184,
            "end_index": 188,
            "id": 13,
            "start_token": 55,
            "end_token": 56,
            "sent_num": 0
        },
        {
            "text": "בקשה_של__הוא של המנכ\"ל לשעבר של החברה להגדיל את העיקול הזמני על נכסי חברת דיור לה_עולה בע\"ם",
            "start_index": 195,
            "end_index": 286,
            "id": 14,
            "start_token": 57,
            "end_token": 81,
            "sent_num": 0
        },
        {
            "text": "_הוא",
            "start_index": 203,
            "end_index": 207,
            "id": 15,
            "start_token": 59,
            "end_token": 60,
            "sent_num": 0
        },
        {
            "text": "המנכ\"ל לשעבר של החברה",
            "start_index": 211,
            "end_index": 232,
            "id": 16,
            "start_token": 61,
            "end_token": 67,
            "sent_num": 0
        },
        {
            "text": "החברה",
            "start_index": 227,
            "end_index": 232,
            "id": 17,
            "start_token": 65,
            "end_token": 67,
            "sent_num": 0
        },
        {
            "text": "העיקול הזמני על נכסי חברת דיור לה_עולה בע\"ם",
            "start_index": 243,
            "end_index": 286,
            "id": 18,
            "start_token": 69,
            "end_token": 81,
            "sent_num": 0
        },
        {
            "text": "נכסי חברת דיור לה_עולה בע\"ם",
            "start_index": 259,
            "end_index": 286,
            "id": 19,
            "start_token": 74,
            "end_token": 81,
            "sent_num": 0
        },
        {
            "text": "חברת דיור לה_עולה בע\"ם",
            "start_index": 264,
            "end_index": 286,
            "id": 20,
            "start_token": 75,
            "end_token": 81,
            "sent_num": 0
        },
        {
            "text": "דיור לה_עולה בע\"ם",
            "start_index": 269,
            "end_index": 286,
            "id": 21,
            "start_token": 76,
            "end_token": 81,
            "sent_num": 0
        },
        {
            "text": "הצו",
            "start_index": 288,
            "end_index": 291,
            "id": 22,
            "start_token": 0,
            "end_token": 2,
            "sent_num": 1
        },
        {
            "text": "החלטת הסוכנות למכור את החברה לאיש-העסקים יוסי דיאמנט",
            "start_index": 315,
            "end_index": 367,
            "id": 23,
            "start_token": 8,
            "end_token": 22,
            "sent_num": 1
        },
        {
            "text": "החברה",
            "start_index": 338,
            "end_index": 343,
            "id": 24,
            "start_token": 13,
            "end_token": 15,
            "sent_num": 1
        },
        {
            "text": "איש-העסקים יוסי דיאמנט",
            "start_index": 345,
            "end_index": 367,
            "id": 26,
            "start_token": 16,
            "end_token": 22,
            "sent_num": 1
        },
        {
            "text": "אהרון דב קמחי",
            "start_index": 369,
            "end_index": 382,
            "id": 27,
            "start_token": 0,
            "end_token": 3,
            "sent_num": 2
        },
        {
            "text": "כעשר שנים",
            "start_index": 387,
            "end_index": 396,
            "id": 28,
            "start_token": 4,
            "end_token": 7,
            "sent_num": 2
        },
        {
            "text": "יו\"ר ומנהל העסקים של חברה-בת של הסוכנות היהודית העוסקת בבנייה: דיור לה_עולה בע\"ם",
            "start_index": 397,
            "end_index": 477,
            "id": 29,
            "start_token": 7,
            "end_token": 31,
            "sent_num": 2
        },
        {
            "text": "מנהל העסקים",
            "start_index": 403,
            "end_index": 414,
            "id": 30,
            "start_token": 9,
            "end_token": 12,
            "sent_num": 2
        },
        {
            "text": "חברה-בת של הסוכנות היהודית העוסקת בבנייה: דיור לה_עולה בע\"ם",
            "start_index": 418,
            "end_index": 477,
            "id": 31,
            "start_token": 13,
            "end_token": 31,
            "sent_num": 2
        },
        {
            "text": "הסוכנות היהודית",
            "start_index": 429,
            "end_index": 444,
            "id": 32,
            "start_token": 17,
            "end_token": 21,
            "sent_num": 2
        },
        {
            "text": "בנייה",
            "start_index": 453,
            "end_index": 458,
            "id": 33,
            "start_token": 24,
            "end_token": 25,
            "sent_num": 2
        },
        {
            "text": "דיור לה_עולה בע\"ם",
            "start_index": 460,
            "end_index": 477,
            "id": 34,
            "start_token": 26,
            "end_token": 31,
            "sent_num": 2
        },
        {
            "text": "קמחי",
            "start_index": 479,
            "end_index": 483,
            "id": 35,
            "start_token": 0,
            "end_token": 1,
            "sent_num": 3
        },
        {
            "text": "תפקיד_של__הוא בדיור לה_עולה",
            "start_index": 490,
            "end_index": 517,
            "id": 36,
            "start_token": 3,
            "end_token": 11,
            "sent_num": 3
        },
        {
            "text": "_הוא",
            "start_index": 499,
            "end_index": 503,
            "id": 37,
            "start_token": 5,
            "end_token": 6,
            "sent_num": 3
        },
        {
            "text": "דיור לה_עולה",
            "start_index": 505,
            "end_index": 517,
            "id": 38,
            "start_token": 7,
            "end_token": 11,
            "sent_num": 3
        },
        {
            "text": "סוף שנת 1987",
            "start_index": 520,
            "end_index": 532,
            "id": 39,
            "start_token": 13,
            "end_token": 16,
            "sent_num": 3
        },
        {
            "text": "נציגי הסוכנות דירקטוריון החברה",
            "start_index": 541,
            "end_index": 571,
            "id": 40,
            "start_token": 20,
            "end_token": 26,
            "sent_num": 3
        },
        {
            "text": "דירקטוריון החברה",
            "start_index": 555,
            "end_index": 571,
            "id": 41,
            "start_token": 23,
            "end_token": 26,
            "sent_num": 3
        },
        {
            "text": "_הוא",
            "start_index": 585,
            "end_index": 589,
            "id": 42,
            "start_token": 31,
            "end_token": 32,
            "sent_num": 3
        },
        {
            "text": "חוזה עבודה מובטח לתקופה קצובה של עוד כשלוש שנים",
            "start_index": 590,
            "end_index": 637,
            "id": 43,
            "start_token": 32,
            "end_token": 43,
            "sent_num": 3
        },
        {
            "text": "תקופה קצובה של עוד כשלוש שנים",
            "start_index": 608,
            "end_index": 637,
            "id": 44,
            "start_token": 36,
            "end_token": 43,
            "sent_num": 3
        },
        {
            "text": "עוד כשלוש שנים",
            "start_index": 623,
            "end_index": 637,
            "id": 45,
            "start_token": 39,
            "end_token": 43,
            "sent_num": 3
        },
        {
            "text": "זאת",
            "start_index": 646,
            "end_index": 649,
            "id": 46,
            "start_token": 1,
            "end_token": 2,
            "sent_num": 4
        },
        {
            "text": "שנת 1988",
            "start_index": 652,
            "end_index": 660,
            "id": 47,
            "start_token": 4,
            "end_token": 6,
            "sent_num": 4
        },
        {
            "text": "קמחי",
            "start_index": 667,
            "end_index": 671,
            "id": 48,
            "start_token": 8,
            "end_token": 9,
            "sent_num": 4
        },
        {
            "text": "עו\"ד חיים ברנזון",
            "start_index": 681,
            "end_index": 697,
            "id": 49,
            "start_token": 11,
            "end_token": 14,
            "sent_num": 4
        },
        {
            "text": "תביעה לבית-הדין לה_עבודה נגד דיור לה_עולה",
            "start_index": 699,
            "end_index": 740,
            "id": 50,
            "start_token": 15,
            "end_token": 29,
            "sent_num": 4
        },
        {
            "text": "בית-הדין לה_עבודה",
            "start_index": 706,
            "end_index": 723,
            "id": 51,
            "start_token": 17,
            "end_token": 24,
            "sent_num": 4
        },
        {
            "text": "דיור לה_עולה",
            "start_index": 728,
            "end_index": 740,
            "id": 52,
            "start_token": 25,
            "end_token": 29,
            "sent_num": 4
        },
        {
            "text": "קמחי",
            "start_index": 742,
            "end_index": 746,
            "id": 53,
            "start_token": 0,
            "end_token": 1,
            "sent_num": 5
        },
        {
            "text": "_הוא",
            "start_index": 760,
            "end_index": 764,
            "id": 54,
            "start_token": 4,
            "end_token": 5,
            "sent_num": 5
        },
        {
            "text": "הפרת חוזה העבודה בטרם עת",
            "start_index": 774,
            "end_index": 798,
            "id": 55,
            "start_token": 7,
            "end_token": 13,
            "sent_num": 5
        },
        {
            "text": "חוזה העבודה",
            "start_index": 779,
            "end_index": 790,
            "id": 56,
            "start_token": 8,
            "end_token": 11,
            "sent_num": 5
        },
        {
            "text": "עת",
            "start_index": 796,
            "end_index": 798,
            "id": 57,
            "start_token": 12,
            "end_token": 13,
            "sent_num": 5
        },
        {
            "text": "_הוא",
            "start_index": 807,
            "end_index": 811,
            "id": 58,
            "start_token": 17,
            "end_token": 18,
            "sent_num": 5
        },
        {
            "text": "פיצויים בגובה שכר_של__הוא הצפוי לה_עתיד",
            "start_index": 812,
            "end_index": 851,
            "id": 59,
            "start_token": 18,
            "end_token": 29,
            "sent_num": 5
        },
        {
            "text": "פיצויים בגובה שכר_של__הוא הצפוי לה_עתיד, פיצויי פטורים מוגדלים בגין שנות העבודה, פדיון חופשה, גמול הודעה מוקדמת וכו",
            "start_index": 812,
            "end_index": 927,
            "id": 60,
            "start_token": 18,
            "end_token": 46,
            "sent_num": 5
        },
        {
            "text": "גובה שכר_של__הוא הצפוי לה_עתיד",
            "start_index": 821,
            "end_index": 851,
            "id": 61,
            "start_token": 20,
            "end_token": 29,
            "sent_num": 5
        },
        {
            "text": "שכר_של__הוא הצפוי לה_עתיד",
            "start_index": 826,
            "end_index": 851,
            "id": 62,
            "start_token": 21,
            "end_token": 29,
            "sent_num": 5
        },
        {
            "text": "_הוא",
            "start_index": 833,
            "end_index": 837,
            "id": 63,
            "start_token": 23,
            "end_token": 24,
            "sent_num": 5
        },
        {
            "text": "ה_עתיד",
            "start_index": 845,
            "end_index": 851,
            "id": 64,
            "start_token": 27,
            "end_token": 29,
            "sent_num": 5
        },
        {
            "text": "פיצויי פטורים מוגדלים בגין שנות העבודה, פדיון חופשה, גמול הודעה מוקדמת וכו",
            "start_index": 853,
            "end_index": 927,
            "id": 65,
            "start_token": 30,
            "end_token": 46,
            "sent_num": 5
        },
        {
            "text": "שנות העבודה",
            "start_index": 880,
            "end_index": 891,
            "id": 66,
            "start_token": 34,
            "end_token": 37,
            "sent_num": 5
        },
        {
            "text": "שנות העבודה, פדיון חופשה, גמול הודעה מוקדמת וכו",
            "start_index": 880,
            "end_index": 927,
            "id": 67,
            "start_token": 34,
            "end_token": 46,
            "sent_num": 5
        },
        {
            "text": "פדיון חופשה",
            "start_index": 893,
            "end_index": 904,
            "id": 68,
            "start_token": 38,
            "end_token": 40,
            "sent_num": 5
        },
        {
            "text": "גמול הודעה מוקדמת",
            "start_index": 906,
            "end_index": 923,
            "id": 69,
            "start_token": 41,
            "end_token": 44,
            "sent_num": 5
        },
        {
            "text": "הודעה מוקדמת",
            "start_index": 911,
            "end_index": 923,
            "id": 70,
            "start_token": 42,
            "end_token": 44,
            "sent_num": 5
        },
        {
            "text": "סכום כולל של כ750 אלף ש\"ח",
            "start_index": 930,
            "end_index": 955,
            "id": 71,
            "start_token": 48,
            "end_token": 55,
            "sent_num": 5
        },
        {
            "text": "הצדדים",
            "start_index": 957,
            "end_index": 963,
            "id": 73,
            "start_token": 0,
            "end_token": 2,
            "sent_num": 6
        },
        {
            "text": "משרדי דיור לה_עולה בתל-אביב",
            "start_index": 985,
            "end_index": 1012,
            "id": 74,
            "start_token": 6,
            "end_token": 15,
            "sent_num": 6
        },
        {
            "text": "דיור לה_עולה",
            "start_index": 991,
            "end_index": 1003,
            "id": 75,
            "start_token": 7,
            "end_token": 11,
            "sent_num": 6
        },
        {
            "text": "סכום של 250 אלף דולר",
            "start_index": 1014,
            "end_index": 1034,
            "id": 77,
            "start_token": 16,
            "end_token": 21,
            "sent_num": 6
        },
        {
            "text": "קמחי",
            "start_index": 1049,
            "end_index": 1053,
            "id": 78,
            "start_token": 26,
            "end_token": 27,
            "sent_num": 6
        },
        {
            "text": "מה לגבות הכספים",
            "start_index": 1060,
            "end_index": 1075,
            "id": 79,
            "start_token": 29,
            "end_token": 33,
            "sent_num": 6
        },
        {
            "text": "הכספים",
            "start_index": 1069,
            "end_index": 1075,
            "id": 80,
            "start_token": 31,
            "end_token": 33,
            "sent_num": 6
        },
        {
            "text": "מקרה שיזכה",
            "start_index": 1077,
            "end_index": 1087,
            "id": 81,
            "start_token": 34,
            "end_token": 37,
            "sent_num": 6
        },
        {
            "text": "בקשה לבית-הדין",
            "start_index": 1090,
            "end_index": 1104,
            "id": 82,
            "start_token": 1,
            "end_token": 7,
            "sent_num": 7
        },
        {
            "text": "בית-הדין",
            "start_index": 1096,
            "end_index": 1104,
            "id": 83,
            "start_token": 3,
            "end_token": 7,
            "sent_num": 7
        },
        {
            "text": "עו\"ד חיים ברנזון",
            "start_index": 1109,
            "end_index": 1125,
            "id": 84,
            "start_token": 8,
            "end_token": 11,
            "sent_num": 7
        },
        {
            "text": "העיקול הישן",
            "start_index": 1129,
            "end_index": 1140,
            "id": 85,
            "start_token": 12,
            "end_token": 16,
            "sent_num": 7
        },
        {
            "text": "שינויים מהותיים",
            "start_index": 1161,
            "end_index": 1176,
            "id": 86,
            "start_token": 21,
            "end_token": 23,
            "sent_num": 7
        },
        {
            "text": "כשנתיים",
            "start_index": 1190,
            "end_index": 1197,
            "id": 87,
            "start_token": 3,
            "end_token": 5,
            "sent_num": 8
        },
        {
            "text": "סכום התביעה",
            "start_index": 1200,
            "end_index": 1211,
            "id": 88,
            "start_token": 7,
            "end_token": 10,
            "sent_num": 8
        },
        {
            "text": "האינפלציה",
            "start_index": 1221,
            "end_index": 1230,
            "id": 89,
            "start_token": 12,
            "end_token": 14,
            "sent_num": 8
        },
        {
            "text": "פסק-דין סופי בבית-הדין האזורי לעבודה, ואולי בערעור ובבג\"ץ",
            "start_index": 1270,
            "end_index": 1327,
            "id": 90,
            "start_token": 5,
            "end_token": 26,
            "sent_num": 9
        },
        {
            "text": "בית-הדין האזורי לעבודה",
            "start_index": 1284,
            "end_index": 1306,
            "id": 91,
            "start_token": 10,
            "end_token": 18,
            "sent_num": 9
        },
        {
            "text": "ערעור",
            "start_index": 1315,
            "end_index": 1320,
            "id": 92,
            "start_token": 22,
            "end_token": 23,
            "sent_num": 9
        },
        {
            "text": "בג\"ץ",
            "start_index": 1323,
            "end_index": 1327,
            "id": 93,
            "start_token": 25,
            "end_token": 26,
            "sent_num": 9
        },
        {
            "text": "זמן רב",
            "start_index": 1335,
            "end_index": 1341,
            "id": 94,
            "start_token": 28,
            "end_token": 30,
            "sent_num": 9
        },
        {
            "text": "סכום התביעה",
            "start_index": 1343,
            "end_index": 1354,
            "id": 95,
            "start_token": 0,
            "end_token": 3,
            "sent_num": 10
        },
        {
            "text": "הסוכנות",
            "start_index": 1381,
            "end_index": 1388,
            "id": 96,
            "start_token": 3,
            "end_token": 5,
            "sent_num": 11
        },
        {
            "text": "מכרז לה_מכירה דיור לה_עולה",
            "start_index": 1396,
            "end_index": 1422,
            "id": 97,
            "start_token": 6,
            "end_token": 14,
            "sent_num": 11
        },
        {
            "text": "ה_מכירה דיור לה_עולה",
            "start_index": 1402,
            "end_index": 1422,
            "id": 98,
            "start_token": 8,
            "end_token": 14,
            "sent_num": 11
        },
        {
            "text": "קמחי",
            "start_index": 1437,
            "end_index": 1441,
            "id": 99,
            "start_token": 18,
            "end_token": 19,
            "sent_num": 11
        },
        {
            "text": "חובות דיור לה_עולה כלפי_הוא",
            "start_index": 1443,
            "end_index": 1470,
            "id": 100,
            "start_token": 20,
            "end_token": 27,
            "sent_num": 11
        },
        {
            "text": "דיור לה_עולה",
            "start_index": 1449,
            "end_index": 1461,
            "id": 101,
            "start_token": 21,
            "end_token": 25,
            "sent_num": 11
        },
        {
            "text": "התובע",
            "start_index": 1482,
            "end_index": 1487,
            "id": 103,
            "start_token": 4,
            "end_token": 6,
            "sent_num": 12
        },
        {
            "text": "ביה\"ד",
            "start_index": 1489,
            "end_index": 1494,
            "id": 104,
            "start_token": 7,
            "end_token": 8,
            "sent_num": 12
        }
    ]
}