{
    "phase": "mentions",
    "clusters": [
        {
            "id": 0,
            "members": [
                0
            ],
            "source": "idiomatic"
        },
        {
            "id": 1,
            "members": [
                1
            ],
            "source": "idiomatic"
        },
        {
            "id": 2,
            "members": [
                2
            ],
            "source": "mention"
        },
        {
            "id": 3,
            "members": [
                3
            ],
            "source": "idiomatic"
        },
        {
            "id": 4,
            "members": [
                4
            ],
            "source": "mention"
        },
        {
            "id": 5,
            "members": [
                5
            ],
            "source": "mention"
        },
        {
            "id": 6,
            "members": [
                6
            ],
            "source": "mention"
        },
        {
            "id": 7,
            "members": [
                7
            ],
            "source": "idiomatic"
        },
        {
            "id": 8,
            "members": [
                8
            ],
            "source": "idiomatic"
        },
        {
            "id": 9,
            "members": [
                9
            ],
            "source": "mention"
        },
        {
            "id": 10,
            "members": [
                10
            ],
            "source": "mention"
        },
        {
            "id": 11,
            "members": [
                11
            ],
            "source": "mention"
        },
        {
            "id": 12,
            "members": [
                12
            ],
            "source": "mention"
        },
        {
            "id": 13,
            "members": [
                13
            ],
            "source": "mention"
        },
        {
            "id": 14,
            "members": [
                14
            ],
            "source": "mention"
        },
        {
            "id": 15,
            "members": [
                15
            ],
            "source": "mention"
        },
        {
            "id": 16,
            "members": [
                16
            ],
            "source": "mention"
        },
        {
            "id": 17,
            "members": [
                17
            ],
            "source": "mention"
        },
        {
            "id": 18,
            "members": [
                18
            ],
            "source": "mention"
        },
        {
            "id": 19,
            "members": [
                19
            ],
            "source": "mention"
        },
        {
            "id": 20,
            "members": [
                20
            ],
            "source": "mention"
        },
        {
            "id": 21,
            "members": [
                21
            ],
            "source": "mention"
        },
        {
            "id": 22,
            "members": [
                22
            ],
            "source": "mention"
        },
        {
            "id": 23,
            "members": [
                23
            ],
            "source": "mention"
        },
        {
            "id": 24,
            "members": [
                24
            ],
            "source": "mention"
        },
        {
            "id": 25,
            "members": [
                25
            ],
            "source": "mention"
        },
        {
            "id": 26,
            "members": [
                26
            ],
            "source": "idiomatic"
        },
        {
            "id": 27,
            "members": [
                27
            ],
            "source": "mention"
        },
        {
            "id": 28,
            "members": [
                28
            ],
            "source": "mention"
        },
        {
            "id": 29,
            "members": [
                29
            ],
            "source": "mention"
        },
        {
            "id": 30,
            "members": [
                30
            ],
            "source": "mention"
        },
        {
            "id": 31,
            "members": [
                31
            ],
            "source": "mention"
        },
        {
            "id": 32,
            "members": [
                32
            ],
            "source": "mention"
        },
        {
            "id": 33,
            "members": [
                33
            ],
            "source": "mention"
        },
        {
            "id": 34,
            "members": [
                34
            ],
            "source": "mention"
        },
        {
            "id": 35,
            "members": [
                35
            ],
            "source": "mention"
        },
        {
            "id": 36,
            "members": [
                36
            ],
            "source": "mention"
        },
        {
            "id": 37,
            "members": [
                37
            ],
            "source": "mention"
        },
        {
            "id": 38,
            "members": [
                38
            ],
            "source": "mention"
        },
        {
            "id": 39,
            "members": [
                39
            ],
            "source": "mention"
        },
        {
            "id": 40,
            "members": [
                40
            ],
            "source": "mention"
        },
        {
            "id": 41,
            "members": [
                41
            ],
            "source": "idiomatic"
        },
        {
            "id": 42,
            "members": [
                42
            ],
            "source": "mention"
        },
        {
            "id": 43,
            "members": [
                43
            ],
            "source": "idiomatic"
        },
        {
            "id": 44,
            "members": [
                44
            ],
            "source": "mention"
        },
        {
            "id": 45,
            "members": [
                45
            ],
            "source": "mention"
        },
        {
            "id": 46,
            "members": [
                46
            ],
            "source": "mention"
        },
        {
            "id": 47,
            "members": [
                47
            ],
            "source": "mention"
        },
        {
            "id": 48,
            "members": [
                48
            ],
            "source": "mention"
        },
        {
            "id": 49,
            "members": [
                49
            ],
            "source": "mention"
        },
        {
            "id": 50,
            "members": [
                50
            ],
            "source": "mention"
        },
        {
            "id": 51,
            "members": [
                51
            ],
            "source": "mention"
        },
        {
            "id": 52,
            "members": [
                52
            ],
            "source": "mention"
        },
        {
            "id": 53,
            "members": [
                53
            ],
            "source": "mention"
        },
        {
            "id": 54,
            "members": [
                54
            ],
            "source": "idiomatic"
        },
        {
            "id": 55,
            "members": [
                55
            ],
            "source": "mention"
        },
        {
            "id": 56,
            "members": [
                56
            ],
            "source": "mention"
        },
        {
            "id": 57,
            "members": [
                57
            ],
            "source": "idiomatic"
        },
        {
            "id": 58,
            "members": [
                58
            ],
            "source": "mention"
        },
        {
            "id": 59,
            "members": [
                59
            ],
            "source": "mention"
        },
        {
            "id": 60,
            "members": [
                60
            ],
            "source": "mention"
        },
        {
            "id": 61,
            "members": [
                61
            ],
            "source": "mention"
        },
        {
            "id": 62,
            "members": [
                62
            ],
            "source": "mention"
        },
        {
            "id": 63,
            "members": [
                63
            ],
            "source": "mention"
        },
        {
            "id": 64,
            "members": [
                64
            ],
            "source": "mention"
        },
        {
            "id": 65,
            "members": [
                65
            ],
            "source": "mention"
        },
        {
            "id": 66,
            "members": [
                66
            ],
            "source": "mention"
        },
        {
            "id": 69,
            "members": [
                69
            ],
            "source": "mention"
        },
        {
            "id": 70,
            "members": [
                70
            ],
            "source": "mention"
        },
        {
            "id": 71,
            "members": [
                67
            ],
            "source": "idiomatic"
        },
        {
            "id": 72,
            "members": [
                68
            ],
            "source": "idiomatic"
        },
        {
            "id": 73,
            "members": [
                71
            ],
            "source": "idiomatic"
        },
        {
            "id": 74,
            "members": [
                72
            ],
            "source": "mention"
        },
        {
            "id": 75,
            "members": [
                73
            ],
            "source": "mention"
        },
        {
            "id": 76,
            "members": [
                74
            ],
            "source": "mention"
        },
        {
            "id": 77,
            "members": [
                75
            ],
            "source": "mention"
        },
        {
            "id": 78,
            "members": [
                76
            ],
            "source": "mention"
        },
        {
            "id": 79,
            "members": [
                77
            ],
            "source": "mention"
        },
        {
            "id": 80,
            "members": [
                78
            ],
            "source": "mention"
        },
        {
            "id": 81,
            "members": [
                79
            ],
            "source": "mention"
        },
        {
            "id": 82,
            "members": [
                80
            ],
            "source": "mention"
        },
        {
            "id": 83,
            "members": [
                81
            ],
            "source": "mention"
        },
        {
            "id": 84,
            "members": [
                82
            ],
            "source": "mention"
        },
        {
            "id": 85,
            "members": [
                83
            ],
            "source": "idiomatic"
        },
        {
            "id": 86,
            "members": [
                84
            ],
            "source": "mention"
        },
        {
            "id": 87,
            "members": [
                85
            ],
            "source": "mention"
        },
        {
            "id": 88,
            "members": [
                86
            ],
            "source": "mention"
        },
        {
            "id": 89,
            "members": [
                87
            ],
            "source": "mention"
        },
        {
            "id": 90,
            "members": [
                88
            ],
            "source": "mention"
        },
        {
            "id": 91,
            "members": [
                89
            ],
            "source": "idiomatic"
        },
        {
            "id": 92,
            "members": [
                90
            ],
            "source": "mention"
        },
        {
            "id": 93,
            "members": [
                91
            ],
            "source": "mention"
        },
        {
            "id": 94,
            "members": [
                92
            ],
            "source": "idiomatic"
        },
        {
            "id": 95,
            "members": [
                93
            ],
            "source": "mention"
        },
        {
            "id": 96,
            "members": [
                94
            ],
            "source": "mention"
        },
        {
            "id": 97,
            "members": [
                95
            ],
            "source": "mention"
        },
        {
            "id": 98,
            "members": [
                96
            ],
            "source": "mention"
        },
        {
            "id": 99,
            "members": [
                97
            ],
            "source": "mention"
        },
        {
            "id": 100,
            "members": [
                98
            ],
            "source": "mention"
        },
        {
            "id": 101,
            "members": [
                99
            ],
            "source": "mention"
        },
        {
            "id": 102,
            "members": [
                100
            ],
            "source": "mention"
        },
        {
            "id": 103,
            "members": [
                101
            ],
            "source": "mention"
        },
        {
            "id": 104,
            "members": [
                102
            ],
            "source": "mention"
        },
        {
            "id": 105,
            "members": [
                103
            ],
            "source": "mention"
        }
    ],
    "states": [],
    "hit_id": 82,
    "nps": [
        {
            "text": "נ מוראלי חשוב",
            "start_index": 7,
            "end_index": 20,
            "id": 0
        },
        {
            "text": "הפועל",
            "start_index": 26,
            "end_index": 31,
            "id": 1
        },
        {
            "text": "הפועל תל אביב",
            "start_index": 26,
            "end_index": 39,
            "id": 2
        },
        {
            "text": "תל אביב",
            "start_index": 32,
            "end_index": 39,
            "id": 3
        },
        {
            "text": "ה_משחק שלא התעלה לרמה גבוהה",
            "start_index": 41,
            "end_index": 68,
            "id": 4
        },
        {
            "text": "רמה גבוהה",
            "start_index": 59,
            "end_index": 68,
            "id": 5
        },
        {
            "text": "המאבק הצמוד",
            "start_index": 76,
            "end_index": 87,
            "id": 6
        },
        {
            "text": "המאבק הצמוד והסיום הדרמאטי, לפני ההארכה",
            "start_index": 76,
            "end_index": 115,
            "id": 7
        },
        {
            "text": "הסיום הדרמאטי, לפני ההארכה",
            "start_index": 89,
            "end_index": 115,
            "id": 8
        },
        {
            "text": "ההארכה",
            "start_index": 109,
            "end_index": 115,
            "id": 9
        },
        {
            "text": "הוא",
            "start_index": 117,
            "end_index": 120,
            "id": 10
        },
        {
            "text": "הפועל",
            "start_index": 139,
            "end_index": 144,
            "id": 11
        },
        {
            "text": "שליטה מוחלטת בה_כדורים החוזרים",
            "start_index": 152,
            "end_index": 182,
            "id": 12
        },
        {
            "text": "ה_כדורים החוזרים",
            "start_index": 166,
            "end_index": 182,
            "id": 13
        },
        {
            "text": "יתרון זה",
            "start_index": 192,
            "end_index": 200,
            "id": 14
        },
        {
            "text": "עשיית נקודות",
            "start_index": 202,
            "end_index": 214,
            "id": 15
        },
        {
            "text": "_הוא",
            "start_index": 224,
            "end_index": 228,
            "id": 16
        },
        {
            "text": "שחקן_של__הוא הגבוהים",
            "start_index": 216,
            "end_index": 236,
            "id": 17
        },
        {
            "text": "טרי",
            "start_index": 238,
            "end_index": 241,
            "id": 18
        },
        {
            "text": "שחקן_של__הוא הגבוהים, טרי וגיבסון",
            "start_index": 216,
            "end_index": 249,
            "id": 19
        },
        {
            "text": "טרי וגיבסון",
            "start_index": 238,
            "end_index": 249,
            "id": 20
        },
        {
            "text": "גיבסון",
            "start_index": 243,
            "end_index": 249,
            "id": 21
        },
        {
            "text": "טירונים",
            "start_index": 259,
            "end_index": 266,
            "id": 22
        },
        {
            "text": "ה_סל",
            "start_index": 273,
            "end_index": 277,
            "id": 23
        },
        {
            "text": "גיבסון",
            "start_index": 281,
            "end_index": 287,
            "id": 24
        },
        {
            "text": "כיסוי דאבל-אף",
            "start_index": 294,
            "end_index": 307,
            "id": 25
        },
        {
            "text": "דאבל-אף",
            "start_index": 300,
            "end_index": 307,
            "id": 26
        },
        {
            "text": "הוא",
            "start_index": 314,
            "end_index": 317,
            "id": 27
        },
        {
            "text": "כדורים",
            "start_index": 331,
            "end_index": 337,
            "id": 28
        },
        {
            "text": "אנדרסון",
            "start_index": 345,
            "end_index": 352,
            "id": 29
        },
        {
            "text": "פרישמן",
            "start_index": 355,
            "end_index": 361,
            "id": 30
        },
        {
            "text": "זאת",
            "start_index": 377,
            "end_index": 380,
            "id": 31
        },
        {
            "text": "נקודות קלות",
            "start_index": 382,
            "end_index": 393,
            "id": 32
        },
        {
            "text": "ניצחון הפועל",
            "start_index": 395,
            "end_index": 407,
            "id": 33
        },
        {
            "text": "אמסלם",
            "start_index": 440,
            "end_index": 445,
            "id": 34
        },
        {
            "text": "לחימה עיקשת של אמסלם ופרישמן",
            "start_index": 425,
            "end_index": 453,
            "id": 35
        },
        {
            "text": "אמסלם ופרישמן",
            "start_index": 440,
            "end_index": 453,
            "id": 36
        },
        {
            "text": "פרישמן",
            "start_index": 447,
            "end_index": 453,
            "id": 37
        },
        {
            "text": "התקפת קבוצה_של__הוא",
            "start_index": 469,
            "end_index": 488,
            "id": 38
        },
        {
            "text": "קבוצה_של__הוא",
            "start_index": 475,
            "end_index": 488,
            "id": 39
        },
        {
            "text": "_הוא",
            "start_index": 484,
            "end_index": 488,
            "id": 40
        },
        {
            "text": "דופי",
            "start_index": 493,
            "end_index": 497,
            "id": 41
        },
        {
            "text": "מכבי רמת גן",
            "start_index": 499,
            "end_index": 510,
            "id": 42
        },
        {
            "text": "רמת גן",
            "start_index": 504,
            "end_index": 510,
            "id": 43
        },
        {
            "text": "ניצחון",
            "start_index": 515,
            "end_index": 521,
            "id": 44
        },
        {
            "text": "מרבית דקות המשחק",
            "start_index": 535,
            "end_index": 551,
            "id": 45
        },
        {
            "text": "הולקומב",
            "start_index": 566,
            "end_index": 573,
            "id": 46
        },
        {
            "text": "שחקני החיזוק הולקומב ופירסון",
            "start_index": 553,
            "end_index": 581,
            "id": 47
        },
        {
            "text": "הולקומב ופירסון",
            "start_index": 566,
            "end_index": 581,
            "id": 48
        },
        {
            "text": "פירסון",
            "start_index": 575,
            "end_index": 581,
            "id": 49
        },
        {
            "text": "_הם",
            "start_index": 598,
            "end_index": 601,
            "id": 50
        },
        {
            "text": "מיכסת הנקודות שמצפים מ_הם",
            "start_index": 611,
            "end_index": 636,
            "id": 51
        },
        {
            "text": "_הם",
            "start_index": 633,
            "end_index": 636,
            "id": 52
        },
        {
            "text": "94 נקודות",
            "start_index": 643,
            "end_index": 652,
            "id": 53
        },
        {
            "text": "מיכסת הנקודות שמצפים מ_הם (ביחד 94 נקודות)",
            "start_index": 611,
            "end_index": 653,
            "id": 54
        },
        {
            "text": "האכזבה",
            "start_index": 655,
            "end_index": 661,
            "id": 55
        },
        {
            "text": "בינו",
            "start_index": 673,
            "end_index": 677,
            "id": 56
        },
        {
            "text": "עושה המשחק",
            "start_index": 715,
            "end_index": 725,
            "id": 57
        },
        {
            "text": "כדורים רבים",
            "start_index": 740,
            "end_index": 751,
            "id": 58
        },
        {
            "text": "הדרמה",
            "start_index": 753,
            "end_index": 758,
            "id": 59
        },
        {
            "text": "שיא_של__היא",
            "start_index": 766,
            "end_index": 777,
            "id": 60
        },
        {
            "text": "_היא",
            "start_index": 773,
            "end_index": 777,
            "id": 61
        },
        {
            "text": "דקות הסיום",
            "start_index": 779,
            "end_index": 789,
            "id": 62
        },
        {
            "text": "סל",
            "start_index": 791,
            "end_index": 793,
            "id": 63
        },
        {
            "text": "סל",
            "start_index": 798,
            "end_index": 800,
            "id": 64
        },
        {
            "text": "ה_דקה ה-83",
            "start_index": 803,
            "end_index": 813,
            "id": 65
        },
        {
            "text": "לוח התוצאות",
            "start_index": 819,
            "end_index": 830,
            "id": 66
        },
        {
            "text": "שוויון 18",
            "start_index": 834,
            "end_index": 843,
            "id": 67
        },
        {
            "text": "75 שניות לה_סיום",
            "start_index": 845,
            "end_index": 861,
            "id": 68
        },
        {
            "text": "ה_סיום",
            "start_index": 855,
            "end_index": 861,
            "id": 69
        },
        {
            "text": "הפועל",
            "start_index": 867,
            "end_index": 872,
            "id": 70
        },
        {
            "text": "יתרון 77 79",
            "start_index": 873,
            "end_index": 884,
            "id": 71
        },
        {
            "text": "שנייה לה_סיום",
            "start_index": 895,
            "end_index": 908,
            "id": 72
        },
        {
            "text": "ה_סיום",
            "start_index": 902,
            "end_index": 908,
            "id": 73
        },
        {
            "text": "עבירה טכנית",
            "start_index": 915,
            "end_index": 926,
            "id": 74
        },
        {
            "text": "קרטר מרמת גן",
            "start_index": 933,
            "end_index": 945,
            "id": 75
        },
        {
            "text": "רמת גן",
            "start_index": 939,
            "end_index": 945,
            "id": 76
        },
        {
            "text": "הוא",
            "start_index": 947,
            "end_index": 950,
            "id": 77
        },
        {
            "text": "שתי זריקות עונשין",
            "start_index": 959,
            "end_index": 976,
            "id": 78
        },
        {
            "text": "רמת גן",
            "start_index": 995,
            "end_index": 1001,
            "id": 79
        },
        {
            "text": "הוצאת הכדור בידי רמת גן שנייה לה_סיום",
            "start_index": 978,
            "end_index": 1015,
            "id": 80
        },
        {
            "text": "שנייה לה_סיום",
            "start_index": 1002,
            "end_index": 1015,
            "id": 81
        },
        {
            "text": "ה_סיום",
            "start_index": 1009,
            "end_index": 1015,
            "id": 82
        },
        {
            "text": "דבר",
            "start_index": 1025,
            "end_index": 1028,
            "id": 83
        },
        {
            "text": "הקבוצות",
            "start_index": 1030,
            "end_index": 1037,
            "id": 84
        },
        {
            "text": "הארכה",
            "start_index": 1047,
            "end_index": 1052,
            "id": 85
        },
        {
            "text": "ה_הארכה",
            "start_index": 1055,
            "end_index": 1062,
            "id": 86
        },
        {
            "text": "ה_מגרש",
            "start_index": 1070,
            "end_index": 1076,
            "id": 87
        },
        {
            "text": "קבוצה אחת בלבד",
            "start_index": 1077,
            "end_index": 1091,
            "id": 88
        },
        {
            "text": "הפועל",
            "start_index": 1093,
            "end_index": 1098,
            "id": 89
        },
        {
            "text": "קבוצה אחת בלבד, הפועל תל אביב",
            "start_index": 1077,
            "end_index": 1106,
            "id": 90
        },
        {
            "text": "הפועל תל אביב",
            "start_index": 1093,
            "end_index": 1106,
            "id": 91
        },
        {
            "text": "תל אביב",
            "start_index": 1099,
            "end_index": 1106,
            "id": 92
        },
        {
            "text": "_היא",
            "start_index": 1120,
            "end_index": 1124,
            "id": 93
        },
        {
            "text": "61 נקודות של_היא מול 4 של רמת גן",
            "start_index": 1108,
            "end_index": 1140,
            "id": 94
        },
        {
            "text": "רמת גן",
            "start_index": 1134,
            "end_index": 1140,
            "id": 95
        },
        {
            "text": "ההבדל",
            "start_index": 1148,
            "end_index": 1153,
            "id": 96
        },
        {
            "text": "המאבק הצמוד והסיום הדרמאטי",
            "start_index": 76,
            "end_index": 102,
            "id": 97
        },
        {
            "text": "הסיום הדרמאטי",
            "start_index": 89,
            "end_index": 102,
            "id": 98
        },
        {
            "text": "המשחק",
            "start_index": 546,
            "end_index": 551,
            "id": 99
        },
        {
            "text": "גבוהי הפועל",
            "start_index": 700,
            "end_index": 711,
            "id": 100
        },
        {
            "text": "עושה המשחק שוורצמן שאיבד כדורים רבים",
            "start_index": 715,
            "end_index": 751,
            "id": 101
        },
        {
            "text": "שוויון",
            "start_index": 834,
            "end_index": 840,
            "id": 102
        },
        {
            "text": "שניות לה_סיום",
            "start_index": 848,
            "end_index": 861,
            "id": 103
        }
    ]
}